scrapy_algova/extensions/error_logger.py
scrapy_algova/middlewares/request_error_logger.py
scrapy_algova/notify/base.py
scrapy_algova/notify/slack.py
scrapy_algova/notify/twilio.py
scrapy_algova/sender/sender.py
scrapy_algova/wait_request.py
scrapy_algova-0.3.2.dist-info/LICENSE
scrapy_algova-0.3.2.dist-info/METADATA
scrapy_algova-0.3.2.dist-info/WHEEL
scrapy_algova-0.3.2.dist-info/RECORD
