Metadata-Version: 2.3
Name: scrapy-algova
Version: 0.3.2
Summary: A small extension to Scrapy that provides a WaitRequest for delayed/polling requests.
License: MIT
Author: Alonso Valdiva
Author-email: alonso@algova.dev
Requires-Python: >=3.7,<4.0
Classifier: License :: OSI Approved :: MIT License
Classifier: Programming Language :: Python :: 3
Classifier: Programming Language :: Python :: 3.7
Classifier: Programming Language :: Python :: 3.8
Classifier: Programming Language :: Python :: 3.9
Classifier: Programming Language :: Python :: 3.10
Classifier: Programming Language :: Python :: 3.11
Classifier: Programming Language :: Python :: 3.12
Classifier: Programming Language :: Python :: 3.13
Requires-Dist: requests (>=2.28.1,<3.0.0)
Requires-Dist: scrapy (>=2.8.0,<3.0.0)
Requires-Dist: twilio (>=7.0.0,<8.0.0)
Requires-Dist: twisted (>=22.0,<23.0)
